Plotting_funcs/Plotting_util_and_other.py
Plotting_funcs/__init__.py
Plotting_funcs/__main__.py
Plotting_funcs/cli.py
Plotting_funcs-0.0.7.dist-info/AUTHORS.rst
Plotting_funcs-0.0.7.dist-info/LICENSE
Plotting_funcs-0.0.7.dist-info/METADATA
Plotting_funcs-0.0.7.dist-info/WHEEL
Plotting_funcs-0.0.7.dist-info/top_level.txt
Plotting_funcs-0.0.7.dist-info/RECORD
